{"venue":"UNSW","rooms":["UNSW1"],"status":"success"}
{"venue":"UNSW","rooms":["UNSW2"],"status":"success"}
{"venue":"UNSW","rooms":["UNSW3"],"status":"success"}
{"venue":"USYD","rooms":["USYD1"],"status":"success"}
{"venue":"USYD","rooms":["USYD2"],"status":"success"}
{"venue":"USYD","rooms":["USYD3"],"status":"success"}
{"venue":"UNSW","rooms":["UNSW1"],"status":"success"}
{"venue":"USYD","rooms":["USYD1"],"status":"success"}
{"venue":"UNSW","rooms":["UNSW1","UNSW2"],"status":"success"}
{"status":"rejected"}
{"status":"rejected"}
{"status":"rejected"}
{"status":"rejected"}
{"status":"rejected"}
[
 {
  "reservations": [
   {
    "start": "2019-03-21",
    "end": "2019-03-21",
    "id": "test_booking_9"
   },
   {
    "start": "2019-03-25",
    "end": "2019-03-29",
    "id": "test_booking_1"
   },
   {
    "start": "2019-03-30",
    "end": "2019-03-30",
    "id": "test_booking_7"
   }
  ],
  "room": "UNSW1"
 },
 {
  "reservations": [
   {
    "start": "2019-03-21",
    "end": "2019-03-21",
    "id": "test_booking_9"
   },
   {
    "start": "2019-03-25",
    "end": "2019-03-29",
    "id": "test_booking_2"
   }
  ],
  "room": "UNSW2"
 },
 {
  "reservations": [{
   "start": "2019-03-25",
   "end": "2019-03-29",
   "id": "test_booking_3"
  }],
  "room": "UNSW3"
 }
]
[
 {
  "reservations": [
   {
    "start": "2019-03-25",
    "end": "2019-03-29",
    "id": "test_booking_4"
   },
   {
    "start": "2019-03-30",
    "end": "2019-03-30",
    "id": "test_booking_8"
   }
  ],
  "room": "USYD1"
 },
 {
  "reservations": [{
   "start": "2019-03-25",
   "end": "2019-03-29",
   "id": "test_booking_5"
  }],
  "room": "USYD2"
 },
 {
  "reservations": [{
   "start": "2019-03-25",
   "end": "2019-03-29",
   "id": "test_booking_6"
  }],
  "room": "USYD3"
 }
]
